mqttled/__init__.py
mqttled/__main__.py
mqttled/config.py
mqttled/led.py
mqttled/ledDriver.py
mqttled/ledHost.py
mqttled/ledrgb.py
mqttled-0.1.2.dist-info/LICENCE
mqttled-0.1.2.dist-info/METADATA
mqttled-0.1.2.dist-info/WHEEL
mqttled-0.1.2.dist-info/entry_points.txt
mqttled-0.1.2.dist-info/top_level.txt
mqttled-0.1.2.dist-info/RECORD
