Metadata-Version: 2.1
Name: mqttled
Version: 0.1.2
Summary: MQTT control of OpenWRT LEDs with optional Home Assistant Discovery
Home-page: https://github.com/trevortrevor/mqttled
Author: Tom Grime
Author-email: tom.grime@gmail.com
License: MIT
Keywords: OpenWRT, mqtt, Home Assistant
Classifier: Programming Language :: Python :: 3
Classifier: License :: OSI Approved :: MIT License
Classifier: Operating System :: POSIX :: BSD
Requires-Python: >=3.9
License-File: LICENCE
Requires-Dist: paho-mqtt (>=1.0)
Requires-Dist: pyyaml (>=6.0)
Requires-Dist: schema (>=0.7.2)
Requires-Dist: netifaces (>=0.10.0)
Requires-Dist: jsonpath-ng (>=1.5.2)
Requires-Dist: pyuci
